zmats/__init__.py
zmats/_version.py
zmats/converter.py
zmats/exceptions.py
zmats/vectors.py
zmats/zmats.py
zmats/tests/__init__.py
zmats/tests/test_converter.py
zmats/tests/test_vectors.py
zmats/tests/test_zmats.py
zmats-0.1.0.dist-info/LICENSE
zmats-0.1.0.dist-info/METADATA
zmats-0.1.0.dist-info/WHEEL
zmats-0.1.0.dist-info/top_level.txt
zmats-0.1.0.dist-info/RECORD
