Metadata-Version: 2.1
Name: zmats
Version: 0.1.0
Summary: UNKNOWN
Home-page: UNKNOWN
Author: Alon Grinberg Dana
Author-email: alongd@mit.edu
License: MIT
Platform: UNKNOWN
